xlc/__init__.py
xlc/attribute.py
xlc/database/__init__.py
xlc/database/langmark.toml
xlc/database/langtags.py
xlc/database/langtags.toml
xlc/database/subtags.py
xlc/language/__init__.py
xlc/language/message.py
xlc/language/segment.py
xlc-0.6.dist-info/LICENSE
xlc-0.6.dist-info/METADATA
xlc-0.6.dist-info/WHEEL
xlc-0.6.dist-info/top_level.txt
xlc-0.6.dist-info/zip-safe
xlc-0.6.dist-info/RECORD
