Metadata-Version: 2.1
Name: xlc
Version: 0.6
Summary: Internationalization(i18n) and Localization(l10n) of Multiple Languages
Home-page: https://github.com/bondbox/xlc/
Author: Mingzhe Zou
Author-email: zoumingzhe@outlook.com
License: GPLv2
Project-URL: Source Code, https://github.com/bondbox/xlc/
Project-URL: Bug Tracker, https://github.com/bondbox/xlc/issues
Project-URL: Documentation, https://github.com/bondbox/xlc/
Keywords: command-line,argparse,argcomplete
Platform: any
Classifier: Programming Language :: Python
Classifier: Programming Language :: Python :: 3
Requires-Python: >=3.8
License-File: LICENSE
Requires-Dist: pycountry
Requires-Dist: toml
